autoed/__init__.py
autoed/autoed.py
autoed/constants.py
autoed/convert.py
autoed/dataset.py
autoed/global_config.py
autoed/metadata.py
autoed/watch.py
autoed/beam_position/__init__.py
autoed/beam_position/beam_center.py
autoed/beam_position/inversion_method.py
autoed/beam_position/maximum_method.py
autoed/beam_position/midpoint_method.py
autoed/beam_position/midpoint_old.py
autoed/beam_position/misc.py
autoed/beam_position/plot.py
autoed/data/relion_slurm_cpu.json
autoed/data/singla_mask.npz
autoed/process/__init__.py
autoed/process/multiplex.py
autoed/process/pipeline.py
autoed/process/plot_spots.py
autoed/process/process_static.py
autoed/process/slurm.py
autoed/report/__init__.py
autoed/report/json_database.py
autoed/report/misc.py
autoed/report/parser.py
autoed/report/report_generator.py
autoed/report/table_entry.py
autoed/report/txt_report.py
autoed/report/template/favicon.png
autoed/report/template/misc.js
autoed/report/template/report.html
autoed/report/template/scripts.js
autoed/report/template/server
autoed/report/template/styles.css
autoed/server/__init__.py
autoed/server/api.py
autoed/server/auth.py
autoed/server/main.py
autoed/utility/__init__.py
autoed/utility/filesystem.py
autoed/utility/misc_functions.py
autoed-0.3.2.dist-info/licenses/LICENSE
autoed-0.3.2.dist-info/METADATA
autoed-0.3.2.dist-info/WHEEL
autoed-0.3.2.dist-info/entry_points.txt
autoed-0.3.2.dist-info/top_level.txt
autoed-0.3.2.dist-info/RECORD
